fime/__init__.py
fime/_version.py
fime/about.py
fime/config.py
fime/data.py
fime/exceptions.py
fime/import_task.py
fime/main.py
fime/progressindicator.py
fime/report.py
fime/settings.py
fime/task_completer.py
fime/task_edit.py
fime/util.py
fime/worklog.py
fime/worklog_rest.py
fime/icons/__init__.py
fime-1.1.2.dist-info/LICENSE
fime-1.1.2.dist-info/METADATA
fime-1.1.2.dist-info/WHEEL
fime-1.1.2.dist-info/entry_points.txt
fime-1.1.2.dist-info/top_level.txt
fime-1.1.2.dist-info/zip-safe
fime-1.1.2.dist-info/RECORD
