Metadata-Version: 2.1
Name: fime
Version: 1.1.2
Summary: Simple time tracking app written with Python and Qt
Home-page: https://git.faerb.it/faerbit/fime
Author: Faerbit
Author-email: faerbit@posteo.net
License: MIT License
Classifier: Programming Language :: Python :: 3
Classifier: License :: OSI Approved :: MIT License
Classifier: Operating System :: OS Independent
Requires-Python: >=3.8
License-File: LICENSE
Requires-Dist: requests
Requires-Dist: requests-futures
Requires-Dist: packaging
Requires-Dist: loguru
Requires-Dist: browser-cookie3
Provides-Extra: qt5
Requires-Dist: PySide2 ; extra == 'qt5'
Provides-Extra: qt6
Requires-Dist: PySide6 ; extra == 'qt6'
